bootstrap_interval/__init__.py
bootstrap_interval/bootstrap_interval.py
bootstrap_interval-0.0.5.dist-info/LICENSE
bootstrap_interval-0.0.5.dist-info/METADATA
bootstrap_interval-0.0.5.dist-info/WHEEL
bootstrap_interval-0.0.5.dist-info/top_level.txt
bootstrap_interval-0.0.5.dist-info/RECORD
